{
    "id": 18279,
    "title": "Batido cremoso de pl\u00e1tano y manzana",
    "_url": "https:\/\/www.lasrecetascocina.com\/batido-cremoso-de-platano-y-manzana\/",
    "image": "\/images\/18279.jpg",
    "recipeCategory": [
        "Postres"
    ],
    "ingredients": [
        "1 pl&aacute;tano",
        "1 manzana",
        "Leche",
        "Az&uacute;car al gusto"
    ],
    "recipeInstructions": [
        "Limpia el pl&aacute;tano y la manzana, p&eacute;lalos y c&oacute;rtalos en trozos. A&ntilde;&aacute;delos al vaso de la batidora junto con el az&uacute;car al gusto y la leche. La cantidad de leche va al gusto, si quieres que el batido quede cremoso a&ntilde;ade leche hasta que casi cubra a la fruta, si de lo contrario lo prefieres m&aacute;s l&iacute;quido a&ntilde;&aacute;dele m&aacute;s leche, tanta como desees.",
        "Bate todo durante unos minutos y listo."
    ],
    "calories": 124
}