{
    "id": 26416,
    "title": "Solomillo de cerdo con palitos de pimiento y zanahoria",
    "_url": "https:\/\/www.lasrecetascocina.com\/solomillo-de-cerdo-con-palitos-de-pimiento-y-zanahoria\/",
    "image": "\/images\/26416.jpg",
    "recipeCategory": [
        "Carnes"
    ],
    "ingredients": [
        "1 solomillo de cerdo",
        "1 pimiento verde",
        "&frac12; pimiento rojo",
        "1 pimiento amarillo",
        "3 zanahorias",
        "Aceite de oliva",
        "Sal",
        "Pimiento",
        "Vinagre de m&oacute;dena"
    ],
    "recipeInstructions": [
        "<strong>Cortamos en palitos <\/strong>los pimientos y las zanahorias.",
        "En una sart&eacute;n ponemos un chorrito de aceite a calentar y <strong>los salteamos<\/strong> hasta que los pimientos est&eacute;n tiernos. Entonces, echamos unas gotitas de vinagre de m&oacute;dena, removemos los palitos y cocinamos un minuto mas. Tened en cuenta que la zanahoria tarda mas en hacerse; si no os gusta &laquo;al dente&raquo; pod&eacute;is echarla en la sart&eacute;n un poco antes de los pimientos.",
        "Mientras los palitos se cocinan, cortamos el <strong>solomillo de cerdo en filetes<\/strong> de aproximadamente 2 cm de grosor. Salpimentamos.",
        "Cuando los palitos de pimiento y zanahoria est&eacute;n hechos,<strong> sellamos la carne <\/strong>en aceite caliente.",
        "Servimos la carne junto con los palitos de pimiento y zanahoria."
    ],
    "calories": 240
}