{
    "id": 29137,
    "title": "Cusc\u00fas con garbanzos y carne de cordero",
    "_url": "https:\/\/www.lasrecetascocina.com\/cuscus-con-garbanzos-y-carne-de-cordero\/",
    "image": "\/images\/29137.jpg",
    "recipeCategory": [
        "Main"
    ],
    "ingredients": [
        "1 cucharada de aceite",
        "260 g de cordero desmigado (restos ya cocinados)",
        "1 diente de ajo",
        "&frac12; cucharadita de piment&oacute;n dulce",
        "&frac12; cucharadita ras el hanout",
        "&frac12; cucharadita de cilantro molido",
        "1 cebolleta",
        "210 g. de garbanzos cocidos",
        "200 g. de tomate triturado",
        "1 hoja de laurel",
        "1 cucharada de menta picada",
        "Sal",
        "Pimienta",
        "&frac12; vasito de agua"
    ],
    "recipeInstructions": [
        "Calentamos el aceite de oliva en una cazuela y <strong>salteamos el cordero<\/strong>.",
        "Incorporamos el ajo picado y todas las especias y removemos un par de minutos.",
        "A&ntilde;adimos despu&eacute;s la <strong>cebolleta picada<\/strong>, el tomate triturado, los garbanzos y el laurel y mezclamos.",
        "Salpimentamos, incorporamos la menta y vertemos el agua.<strong> Llevamos a ebullici&oacute;n<\/strong> y cocinamos 10 minutos hasta que el agua reduzca y la preparaci&oacute;n espese.",
        "<strong>Servimos con cuc&uacute;s<\/strong> reci&eacute;n cocinado."
    ]
}